README.md
setup.py
dmz/__init__.py
dmz/agent.py
dmz/common.py
dmz/direct.py
dmz/server.py
dmz.egg-info/PKG-INFO
dmz.egg-info/SOURCES.txt
dmz.egg-info/dependency_links.txt
dmz.egg-info/top_level.txt