Metadata-Version: 1.1
Name: dmz
Version: 0.9.0
Summary: DMZ proxy
Home-page: https://gitee.com/rushmore/dmz
Author: Rushmore (Leiming Hong)
Author-email: hong.leiming@qq.com
License: LGPL
Keywords: dmz,proxy
Platform: UNKNOWN
Classifier: Intended Audience :: Developers
Classifier: Topic :: Software Development :: Libraries :: Python Modules
Classifier: License :: OSI Approved :: MIT License
Classifier: Programming Language :: Python :: 3.7
